LICENSE.txt
MANIFEST.in
README.md
setup.cfg
setup.py
compander/__init__.py
compander/version.txt
compander.egg-info/PKG-INFO
compander.egg-info/SOURCES.txt
compander.egg-info/dependency_links.txt
compander.egg-info/requires.txt
compander.egg-info/top_level.txt
test/test_compander.py